odoo/addons/base_report_to_printer_mail/README.rst
odoo/addons/base_report_to_printer_mail/__init__.py
odoo/addons/base_report_to_printer_mail/__manifest__.py
odoo/addons/base_report_to_printer_mail/i18n/base_report_to_printer_mail.pot
odoo/addons/base_report_to_printer_mail/i18n/es.po
odoo/addons/base_report_to_printer_mail/i18n/it.po
odoo/addons/base_report_to_printer_mail/i18n/sv.po
odoo/addons/base_report_to_printer_mail/models/__init__.py
odoo/addons/base_report_to_printer_mail/models/mail_template.py
odoo/addons/base_report_to_printer_mail/readme/CONTRIBUTORS.md
odoo/addons/base_report_to_printer_mail/readme/DESCRIPTION.md
odoo/addons/base_report_to_printer_mail/static/description/icon.png
odoo/addons/base_report_to_printer_mail/static/description/index.html
odoo/addons/base_report_to_printer_mail/tests/__init__.py
odoo/addons/base_report_to_printer_mail/tests/test_mail.py
odoo_addon_base_report_to_printer_mail-18.0.1.0.0.3.dist-info/METADATA
odoo_addon_base_report_to_printer_mail-18.0.1.0.0.3.dist-info/WHEEL
odoo_addon_base_report_to_printer_mail-18.0.1.0.0.3.dist-info/top_level.txt
odoo_addon_base_report_to_printer_mail-18.0.1.0.0.3.dist-info/RECORD
